README.md
setup.py
acrawler_cfscrape/__init__.py
acrawler_cfscrape/handler.py
acrawler_cfscrape.egg-info/PKG-INFO
acrawler_cfscrape.egg-info/SOURCES.txt
acrawler_cfscrape.egg-info/dependency_links.txt
acrawler_cfscrape.egg-info/requires.txt
acrawler_cfscrape.egg-info/top_level.txt