Metadata-Version: 2.1
Name: acrawler-cfscrape
Version: 0.0.5
Summary: The handler working with aCrawler and cloudscraper
Home-page: https://github.com/wooddance/acrawler-cfscrape
Author: wooddance
Author-email: zireael.me@gmail.com
License: UNKNOWN
Platform: UNKNOWN
Requires-Python: >=3.6.0
